nyantip/__init__.py
nyantip/actions.py
nyantip/bot.py
nyantip/coin.py
nyantip/const.py
nyantip/rpc.py
nyantip/stats.py
nyantip/user.py
nyantip/util.py
nyantip/templates/address-invalid.tpl
nyantip/templates/announcement.tpl
nyantip/templates/cant-send.tpl
nyantip/templates/confirmation.tpl
nyantip/templates/didnt-understand.tpl
nyantip/templates/footer.tpl
nyantip/templates/history-empty.tpl
nyantip/templates/history.tpl
nyantip/templates/info.tpl
nyantip/templates/no-pending-tips.tpl
nyantip/templates/not-on-reddit.tpl
nyantip/templates/not-registered.tpl
nyantip/templates/pending-tips-declined.tpl
nyantip/templates/tip-already-pending.tpl
nyantip/templates/tip-below-minimum.tpl
nyantip/templates/tip-low-balance.tpl
nyantip/templates/tip-pending.tpl
nyantip/templates/tip-received.tpl
nyantip/templates/tip-went-wrong.tpl
nyantip-0.8.0.dist-info/LICENSE
nyantip-0.8.0.dist-info/METADATA
nyantip-0.8.0.dist-info/WHEEL
nyantip-0.8.0.dist-info/entry_points.txt
nyantip-0.8.0.dist-info/top_level.txt
nyantip-0.8.0.dist-info/RECORD
