Metadata-Version: 2.1
Name: nyantip
Version: 0.8.0
Summary: Nyancoin tip bot for Reddit.
Author: Bryce Boe
Author-email: bbzbryce@gmail.com
License: GPL
Project-URL: Source Code, https://github.com/bboe/nyantip
Requires-Python: ~= 3.6
License-File: LICENSE
Requires-Dist: Jinja2 ~=3.0
Requires-Dist: PyYAML ~=6.0
Requires-Dist: mysqlclient ~=2.2
Requires-Dist: praw ~=7.3
Requires-Dist: python-bitcoinrpc ==1.0
Requires-Dist: sqlalchemy ~=1.4
Provides-Extra: gpg
Requires-Dist: python-gnupg ==0.4.7 ; extra == 'gpg'
Provides-Extra: lint
Requires-Dist: black ; extra == 'lint'
Requires-Dist: flake8 ; extra == 'lint'
Requires-Dist: isort ; extra == 'lint'
